indico_vc_vidyo/__init__.py
indico_vc_vidyo/blueprint.py
indico_vc_vidyo/cli.py
indico_vc_vidyo/controllers.py
indico_vc_vidyo/forms.py
indico_vc_vidyo/http_api.py
indico_vc_vidyo/plugin.py
indico_vc_vidyo/task.py
indico_vc_vidyo/util.py
indico_vc_vidyo/api/__init__.py
indico_vc_vidyo/api/cache.py
indico_vc_vidyo/api/client.py
indico_vc_vidyo/migrations/.no-headers
indico_vc_vidyo/migrations/20170630_1611_6019621fea50_create_tables.py
indico_vc_vidyo/models/__init__.py
indico_vc_vidyo/models/vidyo_extensions.py
indico_vc_vidyo/static/dist/manifest.json
indico_vc_vidyo/static/dist/js/main.564d2eb5.bundle.js
indico_vc_vidyo/static/dist/js/main.564d2eb5.bundle.js.map
indico_vc_vidyo/static/images/logo.png
indico_vc_vidyo/static/images/vidyo_logo_notext.png
indico_vc_vidyo/templates/buttons.html
indico_vc_vidyo/templates/event_buttons.html
indico_vc_vidyo/templates/info_box.html
indico_vc_vidyo/templates/manage_event_info_box.html
indico_vc_vidyo/templates/management_buttons.html
indico_vc_vidyo/templates/vc_room_timetable_buttons.html
indico_vc_vidyo/templates/emails/created.html
indico_vc_vidyo/templates/emails/deleted.html
indico_vc_vidyo/templates/emails/remote_deleted.html
indico_vc_vidyo/translations/messages.pot
indico_vc_vidyo/translations/fr_FR/LC_MESSAGES/messages-js.po
indico_vc_vidyo/translations/fr_FR/LC_MESSAGES/messages.mo
indico_vc_vidyo/translations/fr_FR/LC_MESSAGES/messages.po
indico_plugin_vc_vidyo-2.3.1.dist-info/METADATA
indico_plugin_vc_vidyo-2.3.1.dist-info/WHEEL
indico_plugin_vc_vidyo-2.3.1.dist-info/entry_points.txt
indico_plugin_vc_vidyo-2.3.1.dist-info/top_level.txt
indico_plugin_vc_vidyo-2.3.1.dist-info/RECORD
