Metadata-Version: 2.1
Name: indico-plugin-vc-vidyo
Version: 2.3.1
Summary: Vidyo video-conferencing plugin for Indico
Home-page: https://github.com/indico/indico-plugins
Author: Indico Team
Author-email: indico-team@cern.ch
License: MIT
Platform: UNKNOWN
Classifier: Environment :: Plugins
Classifier: Environment :: Web Environment
Classifier: License :: OSI Approved :: MIT License
Classifier: Programming Language :: Python :: 2.7
Requires-Dist: indico (>=2.3.2.dev0)
Requires-Dist: zeep
